odoo/addons/l10n_ro_payment_receipt_report/README.rst
odoo/addons/l10n_ro_payment_receipt_report/__init__.py
odoo/addons/l10n_ro_payment_receipt_report/__manifest__.py
odoo/addons/l10n_ro_payment_receipt_report/hooks.py
odoo/addons/l10n_ro_payment_receipt_report/payment_receipt_report_restore.xml
odoo/addons/l10n_ro_payment_receipt_report/data/report_paperformat.xml
odoo/addons/l10n_ro_payment_receipt_report/i18n/l10n_ro_payment_receipt_report.pot
odoo/addons/l10n_ro_payment_receipt_report/i18n/ro.po
odoo/addons/l10n_ro_payment_receipt_report/migrations/14.0.2.2.1/pre-migration.py
odoo/addons/l10n_ro_payment_receipt_report/models/__init__.py
odoo/addons/l10n_ro_payment_receipt_report/models/account_bank_statement_line.py
odoo/addons/l10n_ro_payment_receipt_report/readme/CONTRIBUTORS.rst
odoo/addons/l10n_ro_payment_receipt_report/readme/DESCRIPTION.rst
odoo/addons/l10n_ro_payment_receipt_report/readme/INSTALL.rst
odoo/addons/l10n_ro_payment_receipt_report/readme/USAGE.rst
odoo/addons/l10n_ro_payment_receipt_report/static/description/icon.png
odoo/addons/l10n_ro_payment_receipt_report/static/description/icon.svg
odoo/addons/l10n_ro_payment_receipt_report/static/description/index.html
odoo/addons/l10n_ro_payment_receipt_report/views/account_bank_statement_view.xml
odoo/addons/l10n_ro_payment_receipt_report/views/bank_statement_line_report.xml
odoo/addons/l10n_ro_payment_receipt_report/views/payment_receipt_report.xml
odoo/addons/l10n_ro_payment_receipt_report/views/report_bank_statement_line_payment_template.xml
odoo/addons/l10n_ro_payment_receipt_report/views/report_payment_receipt_template.xml
odoo14_addon_l10n_ro_payment_receipt_report-14.0.2.5.0.dist-info/METADATA
odoo14_addon_l10n_ro_payment_receipt_report-14.0.2.5.0.dist-info/WHEEL
odoo14_addon_l10n_ro_payment_receipt_report-14.0.2.5.0.dist-info/top_level.txt
odoo14_addon_l10n_ro_payment_receipt_report-14.0.2.5.0.dist-info/RECORD
